[
  {
    "pk": 1,
    "model": "main.person",
    "fields": {
      "rght": 22,
      "supervisor": null,
      "name": "A",
      "level": 0,
      "lft": 1,
      "tree_id": 1
    }
  },
  {
    "pk": 2,
    "model": "main.person",
    "fields": {
      "rght": 21,
      "supervisor": 1,
      "name": "B",
      "level": 1,
      "lft": 20,
      "tree_id": 1
    }
  },
  {
    "pk": 3,
    "model": "main.person",
    "fields": {
      "rght": 19,
      "supervisor": 1,
      "name": "C",
      "level": 1,
      "lft": 2,
      "tree_id": 1
    }
  },
  {
    "pk": 4,
    "model": "main.person",
    "fields": {
      "rght": 18,
      "supervisor": 2,
      "name": "D",
      "level": 2,
      "lft": 17,
      "tree_id": 1
    }
  },
  {
    "pk": 5,
    "model": "main.person",
    "fields": {
      "rght": 16,
      "supervisor": 2,
      "name": "E",
      "level": 2,
      "lft": 15,
      "tree_id": 1
    }
  },
  {
    "pk": 6,
    "model": "main.person",
    "fields": {
      "rght": 14,
      "supervisor": 2,
      "name": "F",
      "level": 2,
      "lft": 13,
      "tree_id": 1
    }
  },
  {
    "pk": 7,
    "model": "main.person",
    "fields": {
      "rght": 12,
      "supervisor": 3,
      "name": "G",
      "level": 2,
      "lft": 3,
      "tree_id": 1
    }
  },
  {
    "pk": 8,
    "model": "main.person",
    "fields": {
      "rght": 11,
      "supervisor": 4,
      "name": "H",
      "level": 3,
      "lft": 10,
      "tree_id": 1
    }
  },
  {
    "pk": 9,
    "model": "main.person",
    "fields": {
      "rght": 9,
      "supervisor": 6,
      "name": "I",
      "level": 3,
      "lft": 8,
      "tree_id": 1
    }
  },
  {
    "pk": 10,
    "model": "main.person",
    "fields": {
      "rght": 7,
      "supervisor": 7,
      "name": "J",
      "level": 3,
      "lft": 6,
      "tree_id": 1
    }
  },
  {
    "pk": 11,
    "model": "main.person",
    "fields": {
      "rght": 5,
      "supervisor": 7,
      "name": "K",
      "level": 3,
      "lft": 4,
      "tree_id": 1
    }
  },
  {
    "pk": 1,
    "model": "auth.user",
    "fields": {
      "username": "rohan",
      "first_name": "",
      "last_name": "",
      "is_active": true,
      "is_superuser": true,
      "is_staff": true,
      "last_login": "2011-05-25 11:45:57",
      "groups": [],
      "user_permissions": [],
      "password": "sha1$f2374$56902e464092a0593b952edac184217427006206",
      "email": "crodjer@gmail.com",
      "date_joined": "2011-05-25 10:56:08"
    }
  }
]